psdist/__init__.py
psdist/core.py
psdist/cov.py
psdist/density.py
psdist/distance.py
psdist/distributions.py
psdist/hist.py
psdist/utils.py
psdist/plot/__init__.py
psdist/plot/core.py
psdist/plot/grid.py
psdist/plot/hist.py
psdist/plot/points.py
psdist/plot/rc.py
psdist/plot/utils.py
psdist-2.1.4.dist-info/LICENSE
psdist-2.1.4.dist-info/METADATA
psdist-2.1.4.dist-info/WHEEL
psdist-2.1.4.dist-info/top_level.txt
psdist-2.1.4.dist-info/RECORD
