Metadata-Version: 2.2
Name: psdist
Version: 2.1.4
Summary: Analysis tools for phase space distributions
Author: Austin Hoover
License: MIT License
Project-URL: repository, https://github.com/austin-hoover/psdist
Requires-Python: >=3.11
License-File: LICENSE
Requires-Dist: numpy
Requires-Dist: scipy
Requires-Dist: tqdm
Requires-Dist: ipywidgets
Requires-Dist: matplotlib
Requires-Dist: seaborn
Requires-Dist: ultraplot
